{
    "name": "Backend",
    "alias": "backend",
    "description": "",
    "keywords": [],
    "priority": 0,
    "providers": [
        "Modules\\Backend\\Providers\\BackendServiceProvider",
        "Modules\\Backend\\Providers\\FormServiceProvider",
        "Modules\\Backend\\Providers\\HtmlServiceProvider",
        "Modules\\Backend\\Providers\\MenuServiceProvider"
    ],
    "aliases": {},
    "files": [],
    "requires": [],
    "minimumCoreVersion": "0.0.1",
    "title": "",
    "version":"0.0.1",
    "author": "Hafijul islam"
}
